waveorder/__init__.py
waveorder/_version.py
waveorder/background_estimator.py
waveorder/correction.py
waveorder/filter.py
waveorder/focus.py
waveorder/optics.py
waveorder/reconstruct.py
waveorder/sampling.py
waveorder/stokes.py
waveorder/util.py
waveorder/waveorder_reconstructor.py
waveorder/waveorder_simulator.py
waveorder/models/inplane_oriented_thick_pol3d.py
waveorder/models/inplane_oriented_thick_pol3d_vector.py
waveorder/models/isotropic_fluorescent_thick_3d.py
waveorder/models/isotropic_thin_3d.py
waveorder/models/phase_thick_3d.py
waveorder/visuals/jupyter_visuals.py
waveorder/visuals/matplotlib_visuals.py
waveorder/visuals/napari_visuals.py
waveorder/visuals/utils.py
waveorder-2.2.1.dist-info/licenses/LICENSE
waveorder-2.2.1.dist-info/METADATA
waveorder-2.2.1.dist-info/WHEEL
waveorder-2.2.1.dist-info/top_level.txt
waveorder-2.2.1.dist-info/RECORD
