Metadata-Version: 2.4
Name: waveorder
Version: 2.2.1
Summary: Wave-optical simulations and deconvolution of optical properties
Author-email: CZ Biohub SF <compmicro@czbiohub.org>
Maintainer-email: Talon Chandler <talon.chandler@czbiohub.org>, Shalin Mehta <shalin.mehta@czbiohub.org>
License: BSD 3-Clause License
Project-URL: Homepage, https://github.com/mehta-lab/waveorder
Project-URL: Repository, https://github.com/mehta-lab/waveorder
Project-URL: Issues, https://github.com/mehta-lab/waveorder/issues
Keywords: simulation,optics,phase,scattering,polarization,label-free,permittivity,reconstruction-algorithm,qlipp,mipolscope,permittivity-tensor-imaging
Classifier: Development Status :: 4 - Beta
Classifier: Intended Audience :: Science/Research
Classifier: License :: OSI Approved :: BSD License
Classifier: Programming Language :: Python :: 3
Classifier: Programming Language :: Python :: 3.10
Classifier: Programming Language :: Python :: 3.11
Classifier: Programming Language :: Python :: 3.12
Classifier: Topic :: Scientific/Engineering
Classifier: Topic :: Scientific/Engineering :: Image Processing
Classifier: Topic :: Scientific/Engineering :: Bio-Informatics
Classifier: Operating System :: POSIX :: Linux
Classifier: Operating System :: Microsoft :: Windows
Classifier: Operating System :: MacOS
Requires-Python: >=3.10
License-File: LICENSE
Requires-Dist: numpy>=1.24
Requires-Dist: matplotlib>=3.1.1
Requires-Dist: scipy>=1.3.0
Requires-Dist: pywavelets>=1.1.1
Requires-Dist: ipywidgets>=7.5.1
Requires-Dist: torch>=2.4.1
Provides-Extra: dev
Requires-Dist: pytest; extra == "dev"
Requires-Dist: pytest-cov; extra == "dev"
Requires-Dist: black==25.1.0; extra == "dev"
Provides-Extra: examples
Requires-Dist: napari[all]; extra == "examples"
Requires-Dist: jupyter; extra == "examples"
Dynamic: license-file
